{
  "#InputData": "Input data:",
  "#ApproxInterval": "Approx interval:",
  "#FromX": "From X:",
  "#ToX": "To X:",
  "#LangTooltip": "Zmień język.",
  "#DrawingInterval": "Drawing interval:",
  "#MethArgs": "Method arguments:",
  "#NodesCount": "Nodes count:",
  "#Precision": "Precision",
  "#Meth": "( ͡° ͜ʖ ͡°) Math ( ͡° ͜ʖ ͡°)",
  "#Results": "Results:",
  "#ApproxTicks": "Approximation time [ticks]:",
  "#ApproxError": "Approximation error:",
  "#ApproxPolynom": "Approximation polynomial:",
  "#ApproxLineSeries": "Approx",
  "#AccurateLineSeries": "Accurate",

  "#DrawingIntervalChangeMsg": "Drawing interval was adjusted to interpolation interval in order to be displayed well.",
  "#DrawingIntervalChangeTitle": "Adjusting drawing interval.",
  "#CannotParseMsg": "The data you have entered cannot be parsed.",
  "#CannotParseTitle": "Cannot parse!",
  "#InputVals": "Input values manually.",
  "#NodesAmmountExceptionMsg": "There were problems with the nodes entered manually.",
  "#NodesAmmountExceptionTitle": "Manual data entry error!",
  "#UnexpectedExceptionMsg": "Try entering different values or restarting the app.",
  "#UnexpectedExceptionTitle": "Unexpected error encountered!",
  "#IntervalErrorMsg": "The left interval endpoint is bigger then the right one, try changing interval values.",
  "#IntervalErrorTitle": "Invalid interval endpoints!"
}
